{
"type": "FeatureCollection",
                                                                                
"features": [
{ "type": "Feature", "properties": { "STORMNAME": "SANDY", "STORMTYPE": "HU", "ADVDATE": "121026\/1800", "ADVISNUM": "17A", "STORMNUM": 18.0, "FCSTPRD": 72.0, "BASIN": "al", "LAT": 27.1, "LON": -77.1, "VALIDTIME": "26\/1800", "TAU": 6.0, "MAXWIND": 65.0, "GUST": 80.0, "MSLP": 970.0, "TCDVLP": "Hurricane", "DVLBL": "H", "SSNUM": 1.0, "TCDIR": 0.0, "TCSPD": 6.0, "DATELBL": "2:00 PM Fri", "FLDATELBL": "2012-10-26 2:00 PM Fri EDT", "TIMEZONE": "EDT", "STORMSRC": "Tropical Cyclone" }, "geometry": { "type": "Point", "coordinates": [ -77.099998474121094, 27.100000381469727 ] } }
,
{ "type": "Feature", "properties": { "STORMNAME": "SANDY", "STORMTYPE": "HU", "ADVDATE": "121026\/1800", "ADVISNUM": "17A", "STORMNUM": 18.0, "FCSTPRD": 72.0, "BASIN": "al", "LAT": 27.6, "LON": -77.4, "VALIDTIME": "27\/0000", "TAU": 12.0, "MAXWIND": 70.0, "GUST": 85.0, "MSLP": 9999.0, "TCDVLP": "Hurricane", "DVLBL": "H", "SSNUM": 1.0, "TCDIR": 9999.0, "TCSPD": 9999.0, "DATELBL": "8:00 PM Fri", "FLDATELBL": "2012-10-26 8:00 PM Fri EDT", "TIMEZONE": "EDT", "STORMSRC": "Tropical Cyclone" }, "geometry": { "type": "Point", "coordinates": [ -77.400001525878906, 27.600000381469727 ] } }
,
{ "type": "Feature", "properties": { "STORMNAME": "SANDY", "STORMTYPE": "HU", "ADVDATE": "121026\/1800", "ADVISNUM": "17A", "STORMNUM": 18.0, "FCSTPRD": 72.0, "BASIN": "al", "LAT": 28.9, "LON": -76.8, "VALIDTIME": "27\/1200", "TAU": 24.0, "MAXWIND": 65.0, "GUST": 80.0, "MSLP": 9999.0, "TCDVLP": "Hurricane", "DVLBL": "H", "SSNUM": 1.0, "TCDIR": 9999.0, "TCSPD": 9999.0, "DATELBL": "8:00 AM Sat", "FLDATELBL": "2012-10-27 8:00 AM Sat EDT", "TIMEZONE": "EDT", "STORMSRC": "Tropical Cyclone" }, "geometry": { "type": "Point", "coordinates": [ -76.800003051757812, 28.899999618530273 ] } }
,
{ "type": "Feature", "properties": { "STORMNAME": "SANDY", "STORMTYPE": "HU", "ADVDATE": "121026\/1800", "ADVISNUM": "17A", "STORMNUM": 18.0, "FCSTPRD": 72.0, "BASIN": "al", "LAT": 30.5, "LON": -75.5, "VALIDTIME": "28\/0000", "TAU": 36.0, "MAXWIND": 65.0, "GUST": 80.0, "MSLP": 9999.0, "TCDVLP": "Hurricane", "DVLBL": "H", "SSNUM": 1.0, "TCDIR": 9999.0, "TCSPD": 9999.0, "DATELBL": "8:00 PM Sat", "FLDATELBL": "2012-10-27 8:00 PM Sat EDT", "TIMEZONE": "EDT", "STORMSRC": "Tropical Cyclone" }, "geometry": { "type": "Point", "coordinates": [ -75.5, 30.5 ] } }
,
{ "type": "Feature", "properties": { "STORMNAME": "SANDY", "STORMTYPE": "HU", "ADVDATE": "121026\/1800", "ADVISNUM": "17A", "STORMNUM": 18.0, "FCSTPRD": 72.0, "BASIN": "al", "LAT": 32.2, "LON": -73.7, "VALIDTIME": "28\/1200", "TAU": 48.0, "MAXWIND": 70.0, "GUST": 85.0, "MSLP": 9999.0, "TCDVLP": "Hurricane", "DVLBL": "H", "SSNUM": 1.0, "TCDIR": 9999.0, "TCSPD": 9999.0, "DATELBL": "8:00 AM Sun", "FLDATELBL": "2012-10-28 8:00 AM Sun EDT", "TIMEZONE": "EDT", "STORMSRC": "Tropical Cyclone" }, "geometry": { "type": "Point", "coordinates": [ -73.699996948242188, 32.200000762939453 ] } }
,
{ "type": "Feature", "properties": { "STORMNAME": "SANDY", "STORMTYPE": "HU", "ADVDATE": "121026\/1800", "ADVISNUM": "17A", "STORMNUM": 18.0, "FCSTPRD": 72.0, "BASIN": "al", "LAT": 36.0, "LON": -72.5, "VALIDTIME": "29\/1200", "TAU": 72.0, "MAXWIND": 70.0, "GUST": 85.0, "MSLP": 9999.0, "TCDVLP": "Hurricane", "DVLBL": "H", "SSNUM": 1.0, "TCDIR": 9999.0, "TCSPD": 9999.0, "DATELBL": "8:00 AM Mon", "FLDATELBL": "2012-10-29 8:00 AM Mon EDT", "TIMEZONE": "EDT", "STORMSRC": "Tropical Cyclone" }, "geometry": { "type": "Point", "coordinates": [ -72.5, 36.0 ] } }
,
{ "type": "Feature", "properties": { "STORMNAME": "SANDY", "STORMTYPE": "HU", "ADVDATE": "121026\/1800", "ADVISNUM": "17A", "STORMNUM": 18.0, "FCSTPRD": 120.0, "BASIN": "al", "LAT": 27.1, "LON": -77.1, "VALIDTIME": "26\/1800", "TAU": 6.0, "MAXWIND": 65.0, "GUST": 80.0, "MSLP": 970.0, "TCDVLP": "Hurricane", "DVLBL": "H", "SSNUM": 1.0, "TCDIR": 0.0, "TCSPD": 6.0, "DATELBL": "2:00 PM Fri", "FLDATELBL": "2012-10-26 2:00 PM Fri EDT", "TIMEZONE": "EDT", "STORMSRC": "Tropical Cyclone" }, "geometry": { "type": "Point", "coordinates": [ -77.099998474121094, 27.100000381469727 ] } }
,
{ "type": "Feature", "properties": { "STORMNAME": "SANDY", "STORMTYPE": "HU", "ADVDATE": "121026\/1800", "ADVISNUM": "17A", "STORMNUM": 18.0, "FCSTPRD": 120.0, "BASIN": "al", "LAT": 27.6, "LON": -77.4, "VALIDTIME": "27\/0000", "TAU": 12.0, "MAXWIND": 70.0, "GUST": 85.0, "MSLP": 9999.0, "TCDVLP": "Hurricane", "DVLBL": "H", "SSNUM": 1.0, "TCDIR": 9999.0, "TCSPD": 9999.0, "DATELBL": "8:00 PM Fri", "FLDATELBL": "2012-10-26 8:00 PM Fri EDT", "TIMEZONE": "EDT", "STORMSRC": "Tropical Cyclone" }, "geometry": { "type": "Point", "coordinates": [ -77.400001525878906, 27.600000381469727 ] } }
,
{ "type": "Feature", "properties": { "STORMNAME": "SANDY", "STORMTYPE": "HU", "ADVDATE": "121026\/1800", "ADVISNUM": "17A", "STORMNUM": 18.0, "FCSTPRD": 120.0, "BASIN": "al", "LAT": 28.9, "LON": -76.8, "VALIDTIME": "27\/1200", "TAU": 24.0, "MAXWIND": 65.0, "GUST": 80.0, "MSLP": 9999.0, "TCDVLP": "Hurricane", "DVLBL": "H", "SSNUM": 1.0, "TCDIR": 9999.0, "TCSPD": 9999.0, "DATELBL": "8:00 AM Sat", "FLDATELBL": "2012-10-27 8:00 AM Sat EDT", "TIMEZONE": "EDT", "STORMSRC": "Tropical Cyclone" }, "geometry": { "type": "Point", "coordinates": [ -76.800003051757812, 28.899999618530273 ] } }
,
{ "type": "Feature", "properties": { "STORMNAME": "SANDY", "STORMTYPE": "HU", "ADVDATE": "121026\/1800", "ADVISNUM": "17A", "STORMNUM": 18.0, "FCSTPRD": 120.0, "BASIN": "al", "LAT": 30.5, "LON": -75.5, "VALIDTIME": "28\/0000", "TAU": 36.0, "MAXWIND": 65.0, "GUST": 80.0, "MSLP": 9999.0, "TCDVLP": "Hurricane", "DVLBL": "H", "SSNUM": 1.0, "TCDIR": 9999.0, "TCSPD": 9999.0, "DATELBL": "8:00 PM Sat", "FLDATELBL": "2012-10-27 8:00 PM Sat EDT", "TIMEZONE": "EDT", "STORMSRC": "Tropical Cyclone" }, "geometry": { "type": "Point", "coordinates": [ -75.5, 30.5 ] } }
,
{ "type": "Feature", "properties": { "STORMNAME": "SANDY", "STORMTYPE": "HU", "ADVDATE": "121026\/1800", "ADVISNUM": "17A", "STORMNUM": 18.0, "FCSTPRD": 120.0, "BASIN": "al", "LAT": 32.2, "LON": -73.7, "VALIDTIME": "28\/1200", "TAU": 48.0, "MAXWIND": 70.0, "GUST": 85.0, "MSLP": 9999.0, "TCDVLP": "Hurricane", "DVLBL": "H", "SSNUM": 1.0, "TCDIR": 9999.0, "TCSPD": 9999.0, "DATELBL": "8:00 AM Sun", "FLDATELBL": "2012-10-28 8:00 AM Sun EDT", "TIMEZONE": "EDT", "STORMSRC": "Tropical Cyclone" }, "geometry": { "type": "Point", "coordinates": [ -73.699996948242188, 32.200000762939453 ] } }
,
{ "type": "Feature", "properties": { "STORMNAME": "SANDY", "STORMTYPE": "HU", "ADVDATE": "121026\/1800", "ADVISNUM": "17A", "STORMNUM": 18.0, "FCSTPRD": 120.0, "BASIN": "al", "LAT": 36.0, "LON": -72.5, "VALIDTIME": "29\/1200", "TAU": 72.0, "MAXWIND": 70.0, "GUST": 85.0, "MSLP": 9999.0, "TCDVLP": "Hurricane", "DVLBL": "H", "SSNUM": 1.0, "TCDIR": 9999.0, "TCSPD": 9999.0, "DATELBL": "8:00 AM Mon", "FLDATELBL": "2012-10-29 8:00 AM Mon EDT", "TIMEZONE": "EDT", "STORMSRC": "Tropical Cyclone" }, "geometry": { "type": "Point", "coordinates": [ -72.5, 36.0 ] } }
,
{ "type": "Feature", "properties": { "STORMNAME": "SANDY", "STORMTYPE": "HU", "ADVDATE": "121026\/1800", "ADVISNUM": "17A", "STORMNUM": 18.0, "FCSTPRD": 120.0, "BASIN": "al", "LAT": 39.0, "LON": -75.5, "VALIDTIME": "30\/1200", "TAU": 96.0, "MAXWIND": 65.0, "GUST": 80.0, "MSLP": 9999.0, "TCDVLP": "Hurricane", "DVLBL": "H", "SSNUM": 1.0, "TCDIR": 9999.0, "TCSPD": 9999.0, "DATELBL": "8:00 AM Tue", "FLDATELBL": "2012-10-30 8:00 AM Tue EDT", "TIMEZONE": "EDT", "STORMSRC": "Post-Tropical Cyclone" }, "geometry": { "type": "Point", "coordinates": [ -75.5, 39.0 ] } }
,
{ "type": "Feature", "properties": { "STORMNAME": "SANDY", "STORMTYPE": "HU", "ADVDATE": "121026\/1800", "ADVISNUM": "17A", "STORMNUM": 18.0, "FCSTPRD": 120.0, "BASIN": "al", "LAT": 40.5, "LON": -78.0, "VALIDTIME": "31\/1200", "TAU": 120.0, "MAXWIND": 50.0, "GUST": 60.0, "MSLP": 9999.0, "TCDVLP": "Tropical Storm", "DVLBL": "S", "SSNUM": 0.0, "TCDIR": 9999.0, "TCSPD": 9999.0, "DATELBL": "8:00 AM Wed", "FLDATELBL": "2012-10-31 8:00 AM Wed EDT", "TIMEZONE": "EDT", "STORMSRC": "Post-Tropical Cyclone" }, "geometry": { "type": "Point", "coordinates": [ -78.0, 40.5 ] } }

]
}
